fds/verilog/serie02/binary_decoder.v
module binary_decoder (
    input [2:0] in,
    output reg [7:0] out
);

always @*
begin
    
    case (in)
        3'b000: out = 8'b00000001;
        3'b001: out = 8'b00000010;
        3'b010: out = 8'b00000100;
        3'b011: out = 8'b00001000;
        3'b100: out = 8'b00010000;
        3'b101: out = 8'b00100000;
        3'b110: out = 8'b01000000;
        3'b111: out = 8'b10000000;
    endcase

end

endmodule

fds/verilog/serie02/tb_binary_decoder.v
module tb_binary_decoder;

    reg [2:0] in;
    wire [7:0] out;

    binary_decoder decoder (
        .in(in),
        .out(out)
    );

    initial begin
        /* 
        in = 3'b000; // Apply input 000
        #10; // wait for 10 time units
        if (out != 8'b00000001) begin
            $display("Error, wrong input!");
        end
        */
        for (integer i = 0; i < 8; i = i + 1) begin
            in = i;
            #10;
            if (out != 8'b1 << i) begin
                $display("[%d] Error! Wrong Output!", i);
            end else begin
                $display("[%d] Correct Output!", i);
            end
        end
    end

endmodule

fds/verilog/serie02/tb_test.vcd
$date
	Tue Apr  9 12:26:29 2024
$end
$version
	Icarus Verilog
$end
$timescale
	1s
$end
$scope module tb_binary_decoder $end
$var wire 8 ! out [7:0] $end
$var reg 3 " in [2:0] $end
$scope module decoder $end
$var wire 3 # in [2:0] $end
$var reg 8 $ out [7:0] $end
$upscope $end
$scope begin $ivl_for_loop0 $end
$var integer 32 % i [31:0] $end
$upscope $end
$upscope $end
$enddefinitions $end
$comment Show the parameter values. $end
$dumpall
$end
#0
$dumpvars
b0 %
b1 $
b0 #
b0 "
b1 !
$end
#10
b10 !
b10 $
b1 "
b1 #
b1 %
#20
b100 !
b100 $
b10 "
b10 #
b10 %
#30
b1000 !
b1000 $
b11 "
b11 #
b11 %
#40
b10000 !
b10000 $
b100 "
b100 #
b100 %
#50
b100000 !
b100000 $
b101 "
b101 #
b101 %
#60
b1000000 !
b1000000 $
b110 "
b110 #
b110 %
#70
b10000000 !
b10000000 $
b111 "
b111 #
b111 %
#80
b1000 %
