fds/verilog/serie08/DFF.v
module D_FF (
    input clk,
    input reset,
    input set,
    input D,
    output reg Q,
    output reg Q_n
);

// change output
always @(posedge clk) begin
    Q <= reset ? 0 : (set | D);
end

always @* begin
    Q_n = ~Q;
end

endmodule

fds/verilog/serie08/DFF_tb_2.v
module tb_D_FF;
    reg clk, reset, set, D;
    wire Q, Q_n;
    D_FF D_FF_0 (.clk(clk), .reset(reset), .set(set),
    .D(D), .Q(Q), .Q_n(Q_n)
);

initial begin
    $dumpfile("tb_D_FF.vcd");
    $dumpvars(0, tb_D_FF);
    clk = 0; reset = 1; set = 0; D = 1;
    #7;
    D = 0;
    #2;
    reset = 0;
    #3;
    D = 1;
    #5;
    D = 0;
    #10;
    set = 1;
    #13;
    $finish;
end

always begin
    #5 clk = ~clk;
end

endmodule

fds/verilog/serie08/tb_D_FF.vcd
$date
	Mon Apr 15 16:34:16 2024
$end
$version
	Icarus Verilog
$end
$timescale
	1s
$end
$scope module tb_D_FF $end
$var wire 1 ! Q_n $end
$var wire 1 " Q $end
$var reg 1 # D $end
$var reg 1 $ clk $end
$var reg 1 % reset $end
$var reg 1 & set $end
$scope module D_FF_0 $end
$var wire 1 # D $end
$var wire 1 $ clk $end
$var wire 1 % reset $end
$var wire 1 & set $end
$var reg 1 " Q $end
$var reg 1 ! Q_n $end
$upscope $end
$upscope $end
$enddefinitions $end
$comment Show the parameter values. $end
$dumpall
$end
#0
$dumpvars
0&
1%
0$
1#
x"
x!
$end
#5
1!
0"
1$
#7
0#
#9
0%
#10
0$
#12
1#
#15
0!
1"
1$
#17
0#
#20
0$
#25
1!
0"
1$
#27
1&
#30
0$
#35
0!
1"
1$
