fds/verilog/exercise-book/exercise-40/iwannadie.v
module mem (addr_to_read_write, data_in, write_enabled, clock, data_out);

    parameter Nawidth = 3; // address width
    parameter Ndwidth = 8; // data width

    reg [Ndwidth-1:0] mem [2**Nawidth-1:0];

    input write_enabled, clock;
    
    input [Nawidth-1:0] addr_to_read_write;
    input [Ndwidth-1:0] data_in;

    output reg [Ndwidth-1:0] data_out;

    always @(posedge clock) begin

        if (write_enabled) begin
            $display(addr_to_read_write);
            $display(data_in);
            mem[addr_to_read_write] <= data_in;
        end

        data_out <= mem[addr_to_read_write];

    end

endmodule

module memProcessing (
    input clock,
    input Reset,
    input Init,
    input [7:0] DataInA
);

reg [2:0] addr_A_to_read_write;
reg [1:0] addr_B_to_read_write;

reg [7:0] data_to_write_to_B;

reg incA;
reg incB;

reg weA = 0;
reg weB = 0;

wire [7:0] d_out_1;
reg [7:0] d_out_2;

reg [7:0] add_out;
reg [7:0] sub_out;

reg sign;


mem #(.Nawidth(3), .Ndwidth(8)) memoryA (
    .addr_to_read_write(addr_A_to_read_write),
    .data_in(DataInA),
    .write_enabled(weA),
    .clock(clock),
    .data_out(d_out_1)
);

mem #(.Nawidth(2), .Ndwidth(8)) memoryB (
    .addr_to_read_write(addr_B_to_read_write),
    .data_in(data_to_write_to_B),
    .write_enabled(weB),
    .clock(clock)
);

reg [7:0] DataInB;

parameter READA = 2'b00;
parameter COMP = 2'b01;
parameter HALT = 2'b10;

reg [1:0] current_state;
reg [1:0] next_state;

// compute the next state
always @* begin

    next_state = current_state;

    case (current_state)

        READA:
            if (Init) next_state = READA;
            else if (addr_A_to_read_write == 7) begin // we are at the end of the reading of the data in a
                next_state = COMP;
            end else begin
                next_state = READA;
            end

        COMP:
            if (Init) next_state = READA;
            else if (
                addr_A_to_read_write == 0
                && addr_B_to_read_write == 3
            ) begin
                next_state = HALT;
            end else begin
                next_state = COMP;
            end
        
        HALT:
            if (Init) next_state = READA;
            else next_state = HALT;
        
        default: next_state = HALT;

    endcase

end

// assign the next state
always @(posedge clock or posedge Reset) begin
    if (Reset) current_state <= READA;
    else current_state <= next_state;
end

// controller 
always @* begin

    weA = 0;
    weB = 0;
    incA = 0;
    incB = 0;

    case (current_state)

        READA: begin
            weA = 1;
            incA = 1;
            weB = 0;
            incB = 0;
        end

        COMP: begin
            // Never write to A
            weA = 0;
            // Increment A until we finish reading
            // i.e. check if AddrA wrapped around
            if (addr_A_to_read_write == 0 && addr_B_to_read_write == 3) begin
                incA = 0;
            end
            else begin
                incA = 1;
            end
            // Write and increment B every 2 cycles
            // i.e. check the last bit of AddrA
            // and dont write and increment in the first cycle
            if (addr_A_to_read_write[0] == 0 && !(addr_A_to_read_write == 0 && addr_B_to_read_write == 0)) begin
                weB  = 1;
                incB = 1;
            end else begin
                weB  = 0;
                incB = 0;
            end
        end

        HALT: begin
            weA = 0;
            incA = 0;
            weB = 0;
            incB = 0;
        end

        default: begin
            weA = 0;
            incA = 0;
            weB = 0;
            incB = 0;
        end

    endcase

    // if (Init) begin
    //     current_state <= READA;
    //     counterA <= 0;
    //     counterB <= 0;
    // end else begin

    //     if (current_state == READA && counterA != 7) begin
    //         incA = 1;
    //         weA = 1;
    //     end else if (current_state == READA && counterA == 7) begin
    //         weA = 0;
    //     end else if (current_state == COMP && counterB != 3) begin
    //         incB = counterA > 1 && counterA % 2 == 0;
    //         weB = incB;
    //     end else if (current_state == COMP && counterB == 3) begin
    //         current_state = HALT;
    //     end

    //     current_state <= next_state;

    // end

end

always @(posedge clock or posedge Reset) begin

    if (Reset) addr_A_to_read_write <= 0;
    else if (Init) addr_A_to_read_write <= 0;
    else if (incA) addr_A_to_read_write <= addr_A_to_read_write + 1;

end

always @(posedge clock or posedge Reset) begin

    if (Reset) addr_B_to_read_write <= 0;
    else if (Init) addr_B_to_read_write <= 0;
    else if (incB) addr_B_to_read_write <= addr_B_to_read_write + 1;

end

always @(posedge clock or posedge Reset) begin

    if (Reset) d_out_2 <= 0;
    else if (Init) d_out_2 <= 0;
    else d_out_2 <= d_out_1;

end

always @* begin

    add_out = 0;
    sub_out = 0;
    sign = 0;
    data_to_write_to_B = 0;

    add_out = d_out_2 + d_out_1;
    sub_out = d_out_2 - d_out_1;
    sign = d_out_2 <= d_out_1;

    if (sign) data_to_write_to_B = add_out;
    else data_to_write_to_B = sub_out;

end

endmodule

fds/verilog/exercise-book/exercise-40/iwannadie_tb.v
module memProcessingTB ();
    
    reg clk;
    reg [7:0] DataInA;
    reg reset;
    reg Init;

    initial begin
        clk = 0;
        forever #1 clk = ~clk;
    end

    memProcessing uut (
        .clock(clk),
        .Reset(reset),
        .Init(Init),
        .DataInA(DataInA)
    );

    initial begin
        $dumpfile("memProcessingTB.vcd");
        $dumpvars(0, memProcessingTB);

        DataInA = 0;
        reset = 1;
        Init = 1;
        #10 reset = 0;
        #2 Init = 0;
        #2 DataInA = 1;
        #2 DataInA = 2;
        #2 DataInA = 3;
        #2 DataInA = 7;
        #2 DataInA = 6;
        #2 DataInA = 5;
        #2 DataInA = 4;
        // Setting Init to 1 to check the state returns to READA from HALT
        #80 Init = 1;
        #50

        $display(uut.memoryA.mem[0]);

        // check if it is correct
        if (uut.memoryB.mem[0] == 1 && uut.memoryB.mem[1] == 5 && uut.memoryB.mem[2] == 1 && uut.memoryB.mem[3] == 1) begin
            $display("Test passed");
        end else begin
            $display("Test failed");
            $display("Expected: 1 5 1 1");
            $display("Actual: %d %d %d %d", uut.memoryB.mem[0], uut.memoryB.mem[1], uut.memoryB.mem[2], uut.memoryB.mem[3]);
        end
        $finish;
    end
endmodule

fds/verilog/exercise-book/exercise-40/memProcessingTB.vcd
$date
	Tue Jun 25 21:50:28 2024
$end
$version
	Icarus Verilog
$end
$timescale
	1s
$end
$scope module memProcessingTB $end
$var reg 8 ! DataInA [7:0] $end
$var reg 1 " Init $end
$var reg 1 # clk $end
$var reg 1 $ reset $end
$scope module uut $end
$var wire 8 % DataInA [7:0] $end
$var wire 1 " Init $end
$var wire 1 $ Reset $end
$var wire 1 # clock $end
$var wire 8 & d_out_1 [7:0] $end
$var parameter 2 ' COMP $end
$var parameter 2 ( HALT $end
$var parameter 2 ) READA $end
$var reg 8 * add_out [7:0] $end
$var reg 3 + addr_A_to_read_write [2:0] $end
$var reg 2 , addr_B_to_read_write [1:0] $end
$var reg 2 - current_state [1:0] $end
$var reg 8 . d_out_2 [7:0] $end
$var reg 8 / data_to_write_to_B [7:0] $end
$var reg 1 0 incA $end
$var reg 1 1 incB $end
$var reg 2 2 next_state [1:0] $end
$var reg 1 3 sign $end
$var reg 8 4 sub_out [7:0] $end
$var reg 1 5 weA $end
$var reg 1 6 weB $end
$scope module memoryA $end
$var wire 3 7 addr_to_read_write [2:0] $end
$var wire 1 # clock $end
$var wire 8 8 data_in [7:0] $end
$var wire 1 5 write_enabled $end
$var parameter 32 9 Nawidth $end
$var parameter 32 : Ndwidth $end
$var reg 8 ; data_out [7:0] $end
$upscope $end
$scope module memoryB $end
$var wire 2 < addr_to_read_write [1:0] $end
$var wire 1 # clock $end
$var wire 8 = data_in [7:0] $end
$var wire 1 6 write_enabled $end
$var parameter 32 > Nawidth $end
$var parameter 32 ? Ndwidth $end
$var reg 8 @ data_out [7:0] $end
$upscope $end
$upscope $end
$upscope $end
$enddefinitions $end
$comment Show the parameter values. $end
$dumpall
b1000 ?
b10 >
b1000 :
b11 9
b0 )
b10 (
b1 '
$end
#0
$dumpvars
bx @
bx =
b0 <
bx ;
b0 8
b0 7
06
15
bx 4
x3
b0 2
01
10
bx /
b0 .
b0 -
b0 ,
b0 +
bx *
bx &
b0 %
1$
0#
1"
b0 !
$end
#1
1#
#2
0#
#3
b0 /
b0 =
13
b0 4
b0 *
b0 &
b0 ;
1#
#4
0#
#5
1#
#6
0#
#7
1#
#8
0#
#9
1#
#10
0#
0$
#11
1#
#12
0#
0"
#13
10
15
b1 +
b1 7
1#
#14
0#
b1 !
b1 %
b1 8
#15
bx /
bx =
bx 4
bx *
x3
10
15
bx &
bx ;
b10 +
b10 7
1#
#16
0#
b10 !
b10 %
b10 8
#17
bx /
bx =
x3
bx 4
bx *
10
15
bx .
b11 +
b11 7
1#
#18
0#
b11 !
b11 %
b11 8
#19
10
15
b100 +
b100 7
1#
#20
0#
b111 !
b111 %
b111 8
#21
10
15
b101 +
b101 7
1#
#22
0#
b110 !
b110 %
b110 8
#23
10
15
b110 +
b110 7
1#
#24
0#
b101 !
b101 %
b101 8
#25
b1 2
10
15
b111 +
b111 7
1#
#26
0#
b100 !
b100 %
b100 8
#27
10
05
b1 -
b0 +
b0 7
1#
#28
0#
#29
bx /
bx =
x3
bx 4
bx *
10
b0 &
b0 ;
b1 +
b1 7
1#
#30
0#
#31
11
16
10
b1 /
b1 =
13
b11111111 4
b1 *
b1 &
b1 ;
b10 +
b10 7
b0 .
1#
#32
0#
#33
b11 /
b11 =
13
b11111111 4
b11 *
01
10
06
b10 &
b10 ;
b1 .
b1 ,
b1 <
b11 +
b11 7
1#
#34
0#
#35
11
16
10
b101 /
b101 =
13
b11111111 4
b101 *
b11 &
b11 ;
b100 +
b100 7
b10 .
1#
#36
0#
#37
b1010 /
b1010 =
13
b11111100 4
b1010 *
01
10
06
b111 &
b111 ;
b11 .
b10 ,
b10 <
b101 +
b101 7
1#
#38
0#
#39
11
16
10
b1 /
b1 =
03
b1 4
b1101 *
b110 &
b110 ;
b110 +
b110 7
b111 .
1#
#40
0#
#41
b1 /
b1 =
b1 4
b1011 *
01
10
06
b101 &
b101 ;
b110 .
b11 ,
b11 <
b111 +
b111 7
1#
#42
0#
#43
b10 2
11
16
00
b1 /
b1 =
b1 4
b1001 *
b100 &
b100 ;
b0 +
b0 7
b101 .
1#
#44
0#
#45
b100 /
b100 =
b100 4
b100 *
01
06
b0 &
b0 ;
b100 .
b0 ,
b0 <
b10 -
1#
#46
0#
#47
13
b0 /
b0 =
b0 4
b0 *
b1 @
b0 .
1#
