fds/verilog/exercise-book/exercise-18/full_adder/half_adder.v
module half_adder (
    input x1,
    input x2,
    output s,
    output c
);

assign s = x1 ^ x2;
assign c = x1 && x2;

endmodule

fds/verilog/exercise-book/exercise-18/full_adder/full_adder.v
module full_adder2 (
    input x,
    input y,
    input cin,
    output s,
    output cout
);

wire tmp_cout;
wire tmp_2_cout;

half_adder ha (
    .x1(x),
    .x2(y),
    .s(tmp_sum),
    .c(tmp_cout)
);

half_adder ha2 (
    .x1(tmp_sum),
    .x2(cin),
    .s(s),
    .c(tmp_2_cout)
);

assign cout = tmp_cout || tmp_2_cout;

endmodule

fds/verilog/exercise-book/exercise-18/full_adder/full_adder_tb.v
module test_full_adder2;

  // Define three inputs that can procedurally be assigned values.
  reg  x, y, cin;
  // And two outputs that respond to them.
  wire s, cout;

  // Connect them to an instantiated full_adder2 module.
  full_adder2 fa2 (.x(x), .y(y), .cin(cin), .s(s), .cout(cout));

  // Loop variable.
  integer i;

  initial begin
    // Write this test's data to a .vcd file that GTKWave can read.
    $dumpfile ("full_adder2.vcd");
    $dumpvars;

    // Print values whenever they change.
    $monitor ("Time %2t, x=%b, y=%b, cin=%b, s=%b, cout=%b",
              $time, x, y, cin, s, cout);

    // Exhaust all input combinations,
    // each time followed by a delay of 1 time unit.
    for (i = 0; i < 8; i += 1) begin
      // Each variable gets one bit from i.
      // First 0, 0, 0
      // then  0, 0, 1, etc.
      {x, y, cin} = i;
      #1;
    end

    // Done.
    $finish;
  end

endmodule

fds/verilog/exercise-book/exercise-18/full_adder/full_adder2.vcd
$date
	Sun Jun 23 17:10:53 2024
$end
$version
	Icarus Verilog
$end
$timescale
	1s
$end
$scope module test_full_adder2 $end
$var wire 1 ! s $end
$var wire 1 " cout $end
$var reg 1 # cin $end
$var reg 1 $ x $end
$var reg 1 % y $end
$var integer 32 & i [31:0] $end
$scope module fa2 $end
$var wire 1 # cin $end
$var wire 1 " cout $end
$var wire 1 $ x $end
$var wire 1 % y $end
$var wire 1 ' tmp_sum $end
$var wire 1 ( tmp_cout $end
$var wire 1 ) tmp_2_cout $end
$var wire 1 ! s $end
$scope module ha $end
$var wire 1 ( c $end
$var wire 1 ' s $end
$var wire 1 $ x1 $end
$var wire 1 % x2 $end
$upscope $end
$scope module ha2 $end
$var wire 1 ) c $end
$var wire 1 ! s $end
$var wire 1 ' x1 $end
$var wire 1 # x2 $end
$upscope $end
$upscope $end
$upscope $end
$enddefinitions $end
$comment Show the parameter values. $end
$dumpall
$end
#0
$dumpvars
0)
0(
0'
b0 &
0%
0$
0#
0"
0!
$end
#1
1!
1#
b1 &
#2
1'
1!
1%
0#
b10 &
#3
1"
0!
1)
1#
b11 &
#4
0"
1!
0)
1$
0%
0#
b100 &
#5
1"
0!
1)
1#
b101 &
#6
0'
1(
0!
0)
1%
0#
b110 &
#7
1!
1#
b111 &
#8
b1000 &
