fds/verilog/exercise-book/exercise-18/structural_example.v
module structural_example (
    // Three input signals.
    input a,
    input b,
    input c,
    // One output signal.
    output f
);

    // One intermediate wire.
    wire p;
    // Two gates specifying name, output, and inputs.
    and g1 (p, a, b);
    or g2 (f, p, c);

endmodule

fds/verilog/exercise-book/exercise-18/test_structural_example.v
module test_structural_example;

    // Define three inputs that can procedurally
    // be assigned values.
    reg a, b, c;
    // And one output that responds to them.
    wire f;
    // Connect them to an instance of the module being tested.
    structural_example ex (.a(a), .b(b), .c(c), .f(f));
    // Loop variable.
    integer i;
    initial begin
        // Write this test's data to a .vcd file
        // that GTKWave can read.
        $dumpfile ("structural_example.vcd");
        $dumpvars;
        // Print values whenever they change.
        $monitor ("Time %2t, a=%b, b=%b, c=%b, f=%b",
        $time, a, b, c, f);
        // Exhaust all input combinations,
        // each time followed by a delay of 1 time unit.
        for (i = 0; i < 8; i += 1) begin
            // Each variable gets one bit from i.
            // First 0, 0, 0
            // then 0, 0, 1, etc.
            {a, b, c} = i;
            #1;
        end
        // Done.
        $finish;
    end

endmodule

fds/verilog/exercise-book/exercise-18/structural_example.vcd
$date
	Sun Jun 23 16:34:33 2024
$end
$version
	Icarus Verilog
$end
$timescale
	1s
$end
$scope module test_structural_example $end
$var wire 1 ! f $end
$var reg 1 " a $end
$var reg 1 # b $end
$var reg 1 $ c $end
$var integer 32 % i [31:0] $end
$scope module ex $end
$var wire 1 " a $end
$var wire 1 # b $end
$var wire 1 $ c $end
$var wire 1 ! f $end
$var wire 1 & p $end
$upscope $end
$upscope $end
$enddefinitions $end
$comment Show the parameter values. $end
$dumpall
$end
#0
$dumpvars
0&
b0 %
0$
0#
0"
0!
$end
#1
1!
1$
b1 %
#2
0!
1#
0$
b10 %
#3
1!
1$
b11 %
#4
0!
1"
0#
0$
b100 %
#5
1!
1$
b101 %
#6
1&
1!
1#
0$
b110 %
#7
1$
b111 %
#8
b1000 %
