fds/verilog/serie11/circuit_corr.v
module mem (clock, addr, we, data_in, data_out);

    // le nombre de bits de chaque entrée mémoire
    parameter Ndb = 8;
    // le nombre d'entrées mémoires
    parameter Ndw = 8;

    // l'adresse dans laquelle on veut lire/écrire
    input [Ndw-1:0] addr;

    input clock, we;
    input [Ndb-1:0] data_in;
    output reg [Ndb-1:0] data_out;

    reg [Ndb-1:0] mem [2**Ndw-1:0];

    // gestion de l'écriture et de l'output (synchrones)
    always @(posedge clock) begin
        if (we) begin
            mem[addr] = data_in;
        end
        data_out <= mem[addr];
    end

endmodule

module memProcessing (
    input clock,
    input Reset,
    input Init,
    input [7:0] DataInA
    );
    // State definitions
    parameter READA = 2'b00;
    parameter COMP  = 2'b01;
    parameter HALT  = 2'b10;
    // Wire and register definitions
    reg [2:0] AddrA;
    reg [1:0] AddrB;
    wire [7:0] DOut1;
    reg [7:0] DOut2;
    reg [7:0] DataInB;
    reg [7:0] ADDOut;
    reg [7:0] SUBOut;
    reg Sign;
    reg IncA;
    reg IncB;
    reg WEA;
    reg WEB;
    reg [1:0] state;
    reg [1:0] next_state;

    // Memory A
    mem #(.Ndw(3), .Ndb(8)) MemoryA (
        .clock(clock),
        .addr(AddrA),
        .data_in(DataInA),
        .we(WEA),
        .data_out(DOut1)
    );
    // Memory B
    mem #(.Ndw(2), .Ndb(8)) MemoryB (
        .clock(clock),
        .addr(AddrB),
        .data_in(DataInB),
        .we(WEB)
    );

    // State transition logic
    always @(*) begin
        // Initialize
        next_state = state;
        // Assign
        case (state)
            READA:
            if (Init) next_state = READA;
            else if (AddrA == 7)
            next_state = COMP;
            else
            next_state = READA;
            COMP:
            if (Init) next_state = READA;
            else if (AddrA == 0 && AddrB == 3)
            next_state = HALT;
            else
            next_state = COMP;
            HALT:
            if (Init) next_state = READA;
            else next_state      = HALT;
            default:
            next_state = HALT;
        endcase
    end

    // State assignment logic
    always @(posedge clock or posedge Reset) begin
        if (Reset) state <= READA;
        else state       <= next_state;
    end

    // Controller output logic
    always @(*) begin
        // Initialize
        WEA  = 0;
        IncA = 0;
        WEB  = 0;
        IncB = 0;
        // Assign
        case (state)
            READA: begin
                // Write and increment A
                WEA  = 1;
                IncA = 1;
                WEB  = 0;
                IncB = 0;
            end
            COMP: begin
                // Never write to A
                WEA = 0;
                // Increment A until we finish reading
                // i.e. check if AddrA wrapped around
                if (AddrA == 0 && AddrB == 3)
                    IncA = 0;
                else
                    IncA = 1;
                    // Write and increment B every 2 cycles
                    // i.e. check the last bit of AddrA
                    // and dont write and increment in the first cycle
                    if (AddrA[0] == 0 && !(AddrA == 0
                    && AddrB == 0)) begin
                    WEB  = 1;
                    IncB = 1;
                    end else begin
                    WEB  = 0;
                    IncB = 0;
            end
        end
        HALT: begin
            // Halt and do nothing
            WEA  = 0;
            IncA = 0;
            WEB  = 0;
            IncB = 0;
        end
        default: begin
            WEA  = 0;
            IncA = 0;
            WEB  = 0;
            IncB = 0;
        end
        endcase
    end

    // Counter logic for AddrA
    always @(posedge clock or posedge Reset) begin
        if (Reset) AddrA     <= 0;
        else if (Init) AddrA <= 0;
        else if (IncA) AddrA <= AddrA + 1;
    end

    // Counter logic for AddrB
    always @(posedge clock or posedge Reset) begin
        if (Reset) AddrB     <= 0;
        else if (Init) AddrB <= 0;
        else if (IncB) AddrB <= AddrB + 1;
    end

    // DOut2 logic
    always @(posedge clock or posedge Reset) begin
        if (Reset) DOut2     <= 0;
        else if (Init) DOut2 <= 0;
        else DOut2           <= DOut1;
    end

    // Data processing logic
    always @(*) begin
        // Initialize
        ADDOut  = 0;
        SUBOut  = 0;
        Sign    = 0;
        DataInB = 0;
        // Assign
        ADDOut            = DOut2 + DOut1;
        SUBOut            = DOut2 - DOut1;
        Sign              = DOut2 <= DOut1;
        if (Sign) DataInB = ADDOut;
        else DataInB      = SUBOut;
    end

endmodule

fds/verilog/serie11/circuit_tb.v
module memProcessingTB ();
    
    reg clk;
    reg [7:0] DataInA;
    reg reset;
    reg Init;

    initial begin
        clk = 0;
        forever #1 clk = ~clk;
    end

    memProcessing uut (
        .clock(clk),
        .Reset(reset),
        .Init(Init),
        .DataInA(DataInA)
    );

    initial begin
        $dumpfile("memProcessingTB.vcd");
        $dumpvars(0, memProcessingTB);

        DataInA = 0;
        reset = 1;
        Init = 1;
        #10 reset = 0;
        #2 Init = 0;
        #2 DataInA = 1;
        #2 DataInA = 2;
        #2 DataInA = 3;
        #2 DataInA = 7;
        #2 DataInA = 6;
        #2 DataInA = 5;
        #2 DataInA = 4;
        // Setting Init to 1 to check the state returns to READA from HALT
        #80 Init = 1;
        #50

        // check if it is correct
        if (uut.MemoryB.mem[0] == 1 && uut.MemoryB.mem[1] == 5 && uut.MemoryB.mem[2] == 1 && uut.MemoryB.mem[3] == 1) begin
            $display("Test passed");
        end else begin
            $display("Test failed");
            $display("Expected: 1 5 1 1");
            $display("Actual: %d %d %d %d", uut.MemoryB.mem[0], uut.MemoryB.mem[1], uut.MemoryB.mem[2], uut.MemoryB.mem[3]);
        end
        $finish;
    end
endmodule

fds/verilog/serie11/memProcessingTB.vcd
$date
	Mon May  6 22:49:04 2024
$end
$version
	Icarus Verilog
$end
$timescale
	1s
$end
$scope module memProcessingTB $end
$var reg 8 ! DataInA [7:0] $end
$var reg 1 " Init $end
$var reg 1 # clk $end
$var reg 1 $ reset $end
$scope module uut $end
$var wire 8 % DataInA [7:0] $end
$var wire 1 " Init $end
$var wire 1 $ Reset $end
$var wire 1 # clock $end
$var wire 8 & DOut1 [7:0] $end
$var parameter 2 ' COMP $end
$var parameter 2 ( HALT $end
$var parameter 2 ) READA $end
$var reg 8 * ADDOut [7:0] $end
$var reg 3 + AddrA [2:0] $end
$var reg 2 , AddrB [1:0] $end
$var reg 8 - DOut2 [7:0] $end
$var reg 8 . DataInB [7:0] $end
$var reg 1 / IncA $end
$var reg 1 0 IncB $end
$var reg 8 1 SUBOut [7:0] $end
$var reg 1 2 Sign $end
$var reg 1 3 WEA $end
$var reg 1 4 WEB $end
$var reg 2 5 next_state [1:0] $end
$var reg 2 6 state [1:0] $end
$scope module MemoryA $end
$var wire 3 7 addr [2:0] $end
$var wire 1 # clock $end
$var wire 8 8 data_in [7:0] $end
$var wire 1 3 we $end
$var parameter 32 9 Ndb $end
$var parameter 32 : Ndw $end
$var reg 8 ; data_out [7:0] $end
$upscope $end
$scope module MemoryB $end
$var wire 2 < addr [1:0] $end
$var wire 1 # clock $end
$var wire 8 = data_in [7:0] $end
$var wire 1 4 we $end
$var parameter 32 > Ndb $end
$var parameter 32 ? Ndw $end
$var reg 8 @ data_out [7:0] $end
$upscope $end
$upscope $end
$upscope $end
$enddefinitions $end
$comment Show the parameter values. $end
$dumpall
b10 ?
b1000 >
b11 :
b1000 9
b0 )
b10 (
b1 '
$end
#0
$dumpvars
bx @
bx =
b0 <
bx ;
b0 8
b0 7
b0 6
b0 5
04
13
x2
bx 1
00
1/
bx .
b0 -
b0 ,
b0 +
bx *
bx &
b0 %
1$
0#
1"
b0 !
$end
#1
b0 .
b0 =
12
b0 1
b0 *
b0 &
b0 ;
1#
#2
0#
#3
1#
#4
0#
#5
1#
#6
0#
#7
1#
#8
0#
#9
1#
#10
0#
0$
#11
1#
#12
0#
0"
#13
1/
13
b1 +
b1 7
1#
#14
0#
b1 !
b1 %
b1 8
#15
b1 .
b1 =
b11111111 1
b1 *
12
1/
13
b1 &
b1 ;
b10 +
b10 7
1#
#16
0#
b10 !
b10 %
b10 8
#17
b11 .
b11 =
12
b11111111 1
b11 *
1/
13
b10 &
b10 ;
b1 -
b11 +
b11 7
1#
#18
0#
b11 !
b11 %
b11 8
#19
1/
13
b101 .
b101 =
12
b11111111 1
b101 *
b11 &
b11 ;
b100 +
b100 7
b10 -
1#
#20
0#
b111 !
b111 %
b111 8
#21
b1010 .
b1010 =
12
b11111100 1
b1010 *
1/
13
b111 &
b111 ;
b11 -
b101 +
b101 7
1#
#22
0#
b110 !
b110 %
b110 8
#23
1/
13
b1 .
b1 =
02
b1 1
b1101 *
b110 &
b110 ;
b110 +
b110 7
b111 -
1#
#24
0#
b101 !
b101 %
b101 8
#25
b1 .
b1 =
b1 1
b1011 *
b1 5
1/
13
b101 &
b101 ;
b110 -
b111 +
b111 7
1#
#26
0#
b100 !
b100 %
b100 8
#27
1/
03
b1 .
b1 =
b1 1
b1001 *
b100 &
b100 ;
b1 6
b0 +
b0 7
b101 -
1#
#28
0#
#29
b100 .
b100 =
b100 1
b100 *
1/
b0 &
b0 ;
b100 -
b1 +
b1 7
1#
#30
0#
#31
10
14
1/
12
b1 .
b1 =
b11111111 1
b1 *
b1 &
b1 ;
b10 +
b10 7
b0 -
1#
#32
0#
#33
b11 .
b11 =
12
b11111111 1
b11 *
00
04
1/
b10 &
b10 ;
b1 @
b1 -
b1 ,
b1 <
b11 +
b11 7
1#
#34
0#
#35
10
14
1/
b101 .
b101 =
12
b11111111 1
b101 *
bx @
b11 &
b11 ;
b100 +
b100 7
b10 -
1#
#36
0#
#37
b1010 .
b1010 =
12
b11111100 1
b1010 *
00
04
1/
b111 &
b111 ;
b101 @
b11 -
b10 ,
b10 <
b101 +
b101 7
1#
#38
0#
#39
10
14
1/
b1 .
b1 =
02
b1 1
b1101 *
bx @
b110 &
b110 ;
b110 +
b110 7
b111 -
1#
#40
0#
#41
b1 .
b1 =
b1 1
b1011 *
00
04
1/
b101 &
b101 ;
b1 @
b110 -
b11 ,
b11 <
b111 +
b111 7
1#
#42
0#
#43
b10 5
10
14
0/
b1 .
b1 =
b1 1
b1001 *
bx @
b100 &
b100 ;
b0 +
b0 7
b101 -
1#
#44
0#
#45
b100 .
b100 =
b100 1
b100 *
00
04
b0 &
b0 ;
b1 @
b100 -
b0 ,
b0 <
b10 6
1#
#46
0#
#47
12
b0 .
b0 =
b0 1
b0 *
b0 -
1#
