fds/verilog/serie01/full_adder.v
module full_adder1 (
    input x, y, cin,
    output s, cout
);

wire p1, p2, p3;

assign p1 = x ^ y;
assign p2 = x & y;
assign p3 = cin & p1;

assign s = cin ^ p1;
assign cout = p3 | p2;

endmodule

fds/verilog/serie01/full_adder1_tb.v
module test_full_adder1;

  // Define three inputs that can procedurally be assigned values.
  reg  x, y, cin;
  // And two outputs that respond to them.
  wire s, cout;

  // Connect them to an instantiated full_adder1 module.
  full_adder1 fa1 (.x(x), .y(y), .cin(cin), .s(s), .cout(cout));

  // Loop variable.
  integer i;

  initial begin
    // Write this test's data to a .vcd file that GTKWave can read.
    $dumpfile ("full_adder1.vcd");
    $dumpvars;

    // Print values whenever they change.
    $monitor ("Time %2t, x=%b, y=%b, cin=%b, s=%b, cout=%b",
              $time, x, y, cin, s, cout);

    // Exhaust all input combinations,
    // each time followed by a delay of 1 time unit.
    for (i = 0; i < 8; i += 1) begin
      // Each variable gets one bit from i.
      // First 0, 0, 0
      // then  0, 0, 1, etc.
      {x, y, cin} = i;
      #1;
    end

    // Done.
    $finish;
  end

endmodule

fds/verilog/serie01/full_adder1.vcd
$date
	Sat Mar 30 09:43:02 2024
$end
$version
	Icarus Verilog
$end
$timescale
	1s
$end
$scope module test_full_adder1 $end
$var wire 1 ! s $end
$var wire 1 " cout $end
$var reg 1 # cin $end
$var reg 1 $ x $end
$var reg 1 % y $end
$var integer 32 & i [31:0] $end
$scope module fa1 $end
$var wire 1 # cin $end
$var wire 1 " cout $end
$var wire 1 ' p1 $end
$var wire 1 ( p2 $end
$var wire 1 ) p3 $end
$var wire 1 ! s $end
$var wire 1 $ x $end
$var wire 1 % y $end
$upscope $end
$upscope $end
$enddefinitions $end
#0
$dumpvars
0)
0(
0'
b0 &
0%
0$
0#
0"
0!
$end
#1
1!
1#
b1 &
#2
1'
1!
1%
0#
b10 &
#3
1"
1)
0!
1#
b11 &
#4
0"
0)
1!
1$
0%
0#
b100 &
#5
1"
1)
0!
1#
b101 &
#6
0'
1(
0)
0!
1%
0#
b110 &
#7
1!
1#
b111 &
#8
b1000 &
