fds/verilog/serie01/half_adder.v
module half_adder 
(
    input x, y,
    output s, cout
);

assign s = y ^ x;
assign cout = y & x;

endmodule

fds/verilog/serie01/full_adder2.v
module full_adder2 (
    input x, y, cin,
    output s, cout
);

wire intermediate_sum, intermediate_cout, intermediate_sum2, intermediate_cout2;

half_adder ha1 (
    .x(x),
    .y(y),
    .s(intermediate_sum),
    .cout(intermediate_cout)
);

half_adder ha2 (
    .x(cin),
    .y(intermediate_sum),
    .s(s),
    .cout(intermediate_cout2)
);

assign cout = intermediate_cout | intermediate_cout2;

endmodule

fds/verilog/exercise-book/exercise-18/full_adder/full_adder_tb.v
module test_full_adder2;

  // Define three inputs that can procedurally be assigned values.
  reg  x, y, cin;
  // And two outputs that respond to them.
  wire s, cout;

  // Connect them to an instantiated full_adder2 module.
  full_adder2 fa2 (.x(x), .y(y), .cin(cin), .s(s), .cout(cout));

  // Loop variable.
  integer i;

  initial begin
    // Write this test's data to a .vcd file that GTKWave can read.
    $dumpfile ("full_adder2.vcd");
    $dumpvars;

    // Print values whenever they change.
    $monitor ("Time %2t, x=%b, y=%b, cin=%b, s=%b, cout=%b",
              $time, x, y, cin, s, cout);

    // Exhaust all input combinations,
    // each time followed by a delay of 1 time unit.
    for (i = 0; i < 8; i += 1) begin
      // Each variable gets one bit from i.
      // First 0, 0, 0
      // then  0, 0, 1, etc.
      {x, y, cin} = i;
      #1;
    end

    // Done.
    $finish;
  end

endmodule

fds/verilog/serie01/full_adder2.vcd
$date
	Sat Mar 30 09:55:44 2024
$end
$version
	Icarus Verilog
$end
$timescale
	1s
$end
$scope module test_full_adder2 $end
$var wire 1 ! s $end
$var wire 1 " cout $end
$var reg 1 # cin $end
$var reg 1 $ x $end
$var reg 1 % y $end
$var integer 32 & i [31:0] $end
$scope module fa2 $end
$var wire 1 # cin $end
$var wire 1 " cout $end
$var wire 1 $ x $end
$var wire 1 % y $end
$var wire 1 ! s $end
$var wire 1 ' intermediate_sum $end
$var wire 1 ( intermediate_cout2 $end
$var wire 1 ) intermediate_cout $end
$scope module ha1 $end
$var wire 1 ) cout $end
$var wire 1 ' s $end
$var wire 1 $ x $end
$var wire 1 % y $end
$upscope $end
$scope module ha2 $end
$var wire 1 ( cout $end
$var wire 1 ! s $end
$var wire 1 # x $end
$var wire 1 ' y $end
$upscope $end
$upscope $end
$upscope $end
$enddefinitions $end
#0
$dumpvars
0)
0(
0'
b0 &
0%
0$
0#
0"
0!
$end
#1
1!
1#
b1 &
#2
1'
1!
1%
0#
b10 &
#3
1"
0!
1(
1#
b11 &
#4
0"
1!
0(
1$
0%
0#
b100 &
#5
1"
0!
1(
1#
b101 &
#6
0'
1)
0!
0(
1%
0#
b110 &
#7
1!
1#
b111 &
#8
b1000 &
