fds/verilog/serie01/structural_example2.v
module structural_example (
    // Three input signals.
    input a,
    input b,
    input c,
    // One output signal.
    output f
);

    wire p1;
    wire p2;
    wire not_a; // Declaration of wire without initial assignment
    wire not_b; // Declaration of wire without initial assignment

    // Inverting a and b.
    not g0 (not_a, a);
    not g0_1 (not_b, b);

    // Two gates specifying name, output, and inputs.
    nor g3 (f, p1, p2);
    and g2 (p1, not_a, b);
    and g1 (p2, not_b, c);

endmodule

fds/verilog/serie01/structural_example_tb.v
module test_structural_example;

    // Define three inputs that can procedurally
    // be assigned values.
    reg a, b, c;

    // and one output that responds to them
    wire f;

    // Connect them to an instance of the module being tested
    structural_example ex (.a(a), .b(b), .c(c), .f(f));

    // loop variable
    integer i;

    initial begin
        // write this test's data to a .vcd file
        $dumpfile ("structural_example.vcd");
        $dumpvars;

        // Print values whenever they change
        $monitor ("Time %2t, a=%b, b=%b, c=%b, f=%b", $time, a, b, c, f);

        // exhaust all possible input combinations
        for (i = 0; i < 8; i += 1) begin
            // each variable gets one bit of i
            // first 0, 0, 0
            // then 0, 0, 1
            {a, b, c} = i;
            #1;
        end

        $finish;
    end

endmodule

fds/verilog/serie01/structural_example.vcd
$date
	Sat Mar 30 09:34:29 2024
$end
$version
	Icarus Verilog
$end
$timescale
	1s
$end
$scope module test_structural_example $end
$var wire 1 ! f $end
$var reg 1 " a $end
$var reg 1 # b $end
$var reg 1 $ c $end
$var integer 32 % i [31:0] $end
$scope module ex $end
$var wire 1 " a $end
$var wire 1 # b $end
$var wire 1 $ c $end
$var wire 1 ! f $end
$var wire 1 & not_a $end
$var wire 1 ' not_b $end
$var wire 1 ( p1 $end
$var wire 1 ) p2 $end
$upscope $end
$upscope $end
$enddefinitions $end
#0
$dumpvars
0)
0(
1'
1&
b0 %
0$
0#
0"
1!
$end
#1
0!
1)
1$
b1 %
#2
0'
1(
0)
1#
0$
b10 %
#3
1$
b11 %
#4
1!
0&
1'
0(
1"
0#
0$
b100 %
#5
0!
1)
1$
b101 %
#6
1!
0'
0)
1#
0$
b110 %
#7
1$
b111 %
#8
b1000 %
