fds/verilog/serie09/counter_circuit.v
module counter_circuit(
	input clk,
	input clr,
	output reg [3:0] X,
	output reg [3:0] Y
);

always @(posedge clk) begin

	X <= clr ? 0 : X == 9 ? 0 : X + 1;
	Y <= clr ? 0 : X == 0 ? Y == 9 ? 0 : Y + 1 : Y;

end


endmodule;

fds/verilog/exercise-book/exercise-28/tb_counter_circuit.v
module tb_counter_circuit;
    reg clk, clr;
    wire [3:0] X, Y;

    counter_circuit DUT(
        .clk(clk),
        .clr(clr),
        .X(X),
        .Y(Y)
    );

    initial begin
        $dumpfile("tb_counter_circuit.vcd");
        $dumpvars(0, tb_counter_circuit);

        clk = 0;
        clr = 1;
        #10 clr = 0;
        #5 $display("Y = %d, X = %d", X, Y);
        for(integer i = 0; i < 103; i = i + 1) begin
            #10 $display("Y = %d, X = %d", Y, X);
        end
        $finish;
    end

    always begin
        #5 clk = ~clk;
    end

endmodule

fds/verilog/serie09/tb_counter_circuit.vcd
$date
	Thu Apr 25 16:08:17 2024
$end
$version
	Icarus Verilog
$end
$timescale
	1s
$end
$scope module tb_counter_circuit $end
$var wire 4 ! Y [3:0] $end
$var wire 4 " X [3:0] $end
$var reg 1 # clk $end
$var reg 1 $ clr $end
$scope module DUT $end
$var wire 1 # clk $end
$var wire 1 $ clr $end
$var reg 4 % X [3:0] $end
$var reg 4 & Y [3:0] $end
$upscope $end
$scope begin $ivl_for_loop0 $end
$var integer 32 ' i [31:0] $end
$upscope $end
$upscope $end
$enddefinitions $end
$comment Show the parameter values. $end
$dumpall
$end
#0
$dumpvars
bx '
bx &
bx %
1$
0#
bx "
bx !
$end
#5
b0 !
b0 &
b0 "
b0 %
1#
#10
0#
0$
#15
b1 !
b1 &
b1 "
b1 %
1#
b0 '
#20
0#
#25
b10 "
b10 %
1#
b1 '
#30
0#
#35
b11 "
b11 %
1#
b10 '
#40
0#
#45
b100 "
b100 %
1#
b11 '
#50
0#
#55
b101 "
b101 %
1#
b100 '
#60
0#
#65
b110 "
b110 %
1#
b101 '
#70
0#
#75
b111 "
b111 %
1#
b110 '
#80
0#
#85
b1000 "
b1000 %
1#
b111 '
#90
0#
#95
b1001 "
b1001 %
1#
b1000 '
#100
0#
#105
b0 "
b0 %
1#
b1001 '
#110
0#
#115
b10 !
b10 &
b1 "
b1 %
1#
b1010 '
#120
0#
#125
b10 "
b10 %
1#
b1011 '
#130
0#
#135
b11 "
b11 %
1#
b1100 '
#140
0#
#145
b100 "
b100 %
1#
b1101 '
#150
0#
#155
b101 "
b101 %
1#
b1110 '
#160
0#
#165
b110 "
b110 %
1#
b1111 '
#170
0#
#175
b111 "
b111 %
1#
b10000 '
#180
0#
#185
b1000 "
b1000 %
1#
b10001 '
#190
0#
#195
b1001 "
b1001 %
1#
b10010 '
#200
0#
#205
b0 "
b0 %
1#
b10011 '
#210
0#
#215
b11 !
b11 &
b1 "
b1 %
1#
b10100 '
#220
0#
#225
b10 "
b10 %
1#
b10101 '
#230
0#
#235
b11 "
b11 %
1#
b10110 '
#240
0#
#245
b100 "
b100 %
1#
b10111 '
#250
0#
#255
b101 "
b101 %
1#
b11000 '
#260
0#
#265
b110 "
b110 %
1#
b11001 '
#270
0#
#275
b111 "
b111 %
1#
b11010 '
#280
0#
#285
b1000 "
b1000 %
1#
b11011 '
#290
0#
#295
b1001 "
b1001 %
1#
b11100 '
#300
0#
#305
b0 "
b0 %
1#
b11101 '
#310
0#
#315
b100 !
b100 &
b1 "
b1 %
1#
b11110 '
#320
0#
#325
b10 "
b10 %
1#
b11111 '
#330
0#
#335
b11 "
b11 %
1#
b100000 '
#340
0#
#345
b100 "
b100 %
1#
b100001 '
#350
0#
#355
b101 "
b101 %
1#
b100010 '
#360
0#
#365
b110 "
b110 %
1#
b100011 '
#370
0#
#375
b111 "
b111 %
1#
b100100 '
#380
0#
#385
b1000 "
b1000 %
1#
b100101 '
#390
0#
#395
b1001 "
b1001 %
1#
b100110 '
#400
0#
#405
b0 "
b0 %
1#
b100111 '
#410
0#
#415
b101 !
b101 &
b1 "
b1 %
1#
b101000 '
#420
0#
#425
b10 "
b10 %
1#
b101001 '
#430
0#
#435
b11 "
b11 %
1#
b101010 '
#440
0#
#445
b100 "
b100 %
1#
b101011 '
#450
0#
#455
b101 "
b101 %
1#
b101100 '
#460
0#
#465
b110 "
b110 %
1#
b101101 '
#470
0#
#475
b111 "
b111 %
1#
b101110 '
#480
0#
#485
b1000 "
b1000 %
1#
b101111 '
#490
0#
#495
b1001 "
b1001 %
1#
b110000 '
#500
0#
#505
b0 "
b0 %
1#
b110001 '
#510
0#
#515
b110 !
b110 &
b1 "
b1 %
1#
b110010 '
#520
0#
#525
b10 "
b10 %
1#
b110011 '
#530
0#
#535
b11 "
b11 %
1#
b110100 '
#540
0#
#545
b100 "
b100 %
1#
b110101 '
#550
0#
#555
b101 "
b101 %
1#
b110110 '
#560
0#
#565
b110 "
b110 %
1#
b110111 '
#570
0#
#575
b111 "
b111 %
1#
b111000 '
#580
0#
#585
b1000 "
b1000 %
1#
b111001 '
#590
0#
#595
b1001 "
b1001 %
1#
b111010 '
#600
0#
#605
b0 "
b0 %
1#
b111011 '
#610
0#
#615
b111 !
b111 &
b1 "
b1 %
1#
b111100 '
#620
0#
#625
b10 "
b10 %
1#
b111101 '
#630
0#
#635
b11 "
b11 %
1#
b111110 '
#640
0#
#645
b100 "
b100 %
1#
b111111 '
#650
0#
#655
b101 "
b101 %
1#
b1000000 '
#660
0#
#665
b110 "
b110 %
1#
b1000001 '
#670
0#
#675
b111 "
b111 %
1#
b1000010 '
#680
0#
#685
b1000 "
b1000 %
1#
b1000011 '
#690
0#
#695
b1001 "
b1001 %
1#
b1000100 '
#700
0#
#705
b0 "
b0 %
1#
b1000101 '
#710
0#
#715
b1000 !
b1000 &
b1 "
b1 %
1#
b1000110 '
#720
0#
#725
b10 "
b10 %
1#
b1000111 '
#730
0#
#735
b11 "
b11 %
1#
b1001000 '
#740
0#
#745
b100 "
b100 %
1#
b1001001 '
#750
0#
#755
b101 "
b101 %
1#
b1001010 '
#760
0#
#765
b110 "
b110 %
1#
b1001011 '
#770
0#
#775
b111 "
b111 %
1#
b1001100 '
#780
0#
#785
b1000 "
b1000 %
1#
b1001101 '
#790
0#
#795
b1001 "
b1001 %
1#
b1001110 '
#800
0#
#805
b0 "
b0 %
1#
b1001111 '
#810
0#
#815
b1001 !
b1001 &
b1 "
b1 %
1#
b1010000 '
#820
0#
#825
b10 "
b10 %
1#
b1010001 '
#830
0#
#835
b11 "
b11 %
1#
b1010010 '
#840
0#
#845
b100 "
b100 %
1#
b1010011 '
#850
0#
#855
b101 "
b101 %
1#
b1010100 '
#860
0#
#865
b110 "
b110 %
1#
b1010101 '
#870
0#
#875
b111 "
b111 %
1#
b1010110 '
#880
0#
#885
b1000 "
b1000 %
1#
b1010111 '
#890
0#
#895
b1001 "
b1001 %
1#
b1011000 '
#900
0#
#905
b0 "
b0 %
1#
b1011001 '
#910
0#
#915
b0 !
b0 &
b1 "
b1 %
1#
b1011010 '
#920
0#
#925
b10 "
b10 %
1#
b1011011 '
#930
0#
#935
b11 "
b11 %
1#
b1011100 '
#940
0#
#945
b100 "
b100 %
1#
b1011101 '
#950
0#
#955
b101 "
b101 %
1#
b1011110 '
#960
0#
#965
b110 "
b110 %
1#
b1011111 '
#970
0#
#975
b111 "
b111 %
1#
b1100000 '
#980
0#
#985
b1000 "
b1000 %
1#
b1100001 '
#990
0#
#995
b1001 "
b1001 %
1#
b1100010 '
#1000
0#
#1005
b0 "
b0 %
1#
b1100011 '
#1010
0#
#1015
b1 !
b1 &
b1 "
b1 %
1#
b1100100 '
#1020
0#
#1025
b10 "
b10 %
1#
b1100101 '
#1030
0#
#1035
b11 "
b11 %
1#
b1100110 '
#1040
0#
#1045
b100 "
b100 %
1#
b1100111 '
